{"title":"23/10/2024 New Alzheimer's drug rejected for widespread use in NHS in England","link":"http://www.bbc.co.uk/programmes/m00244m6","pubDate":"Wed, 23 Oct 2024 17:39:00 +0000","enclosure":{"url":"http://open.live.bbc.co.uk/mediaselector/6/redir/version/2.0/mediaset/audio-nondrm-download-rss/proto/http/vpid/p0jzq5pg.mp3","length":"29664000","type":"audio/mpeg"},"content":"<p>The health spending watchdog said it was too expensive for too little benefit</p>","contentSnippet":"The health spending watchdog said it was too expensive for too little benefit","guid":"urn:bbc:podcast:m00244m6","isoDate":"2024-10-23T17:39:00.000Z","itunes":{"author":"BBC Radio 4","subtitle":"The health spending watchdog said it was too expensive for too little benefit","summary":"<p>The health spending watchdog said it was too expensive for too little benefit</p>","explicit":"clean","duration":"1854"}}