{"speakers": [], "chunks": [{"timestamp": [0.0, 1.76], "text": " This is the BBC."}, {"timestamp": [3.28, 6.64], "text": " This podcast is supported by advertising outside the UK."}, {"timestamp": [7.88, 11.58], "text": " This Leicester Dolokyunsichy for BBC Radio Nengale."}, {"timestamp": [12.4, 16.42], "text": " This is Leicester Dolokyunsochy from BBC Radio Nongale."}, {"timestamp": [17.74, 24.48], "text": " In this is Leicester Dolokgynous, Lear-Oarie Makhiela, 3'8 in the Hain."}, {"timestamp": [25.0, 31.0], "text": " Rory MacGillane. This is 1,037 in one. Then, the Tours Soule on the Sion Hounthus, my clovour."}, {"timestamp": [31.0, 37.0], "text": " He is scribed with Rourie Campbell in Minard on Clotach Loughfine,"}, {"timestamp": [37.0, 40.0], "text": " to find a fash on two years."}, {"timestamp": [40.0, 46.0], "text": " In Chacken in the Chai, that the Sule is, as a few in the year"}, {"timestamp": [46.0, 48.0], "text": " in the Chowah"}, {"timestamp": [48.0, 50.0], "text": " the Chowah"}, {"timestamp": [50.0, 51.0], "text": " the Choram."}, {"timestamp": [51.0, 52.0], "text": " In the day,"}, {"timestamp": [52.0, 53.0], "text": " I'm a dole of horse"}, {"timestamp": [53.0, 54.0], "text": " soul,"}, {"timestamp": [54.0, 57.0], "text": " it's the daugan"}, {"timestamp": [57.0, 59.0], "text": " there's the people"}, {"timestamp": [59.0, 60.0], "text": " clackagg,"}, {"timestamp": [60.0, 61.0], "text": " Dullas,"}, {"timestamp": [61.0, 64.0], "text": " and Dullachfah"}, {"timestamp": [64.0, 68.0], "text": " Chorchee. Crochol, that'sesk, and Dullachfair. Croftel, that's short of Lichen,"}, {"timestamp": [68.0, 70.0], "text": " a farce, in the Crickon."}, {"timestamp": [70.0, 73.0], "text": " Dulles, that's finem,"}, {"timestamp": [73.0, 76.0], "text": " Dals, on in the Beirla,"}, {"timestamp": [76.0, 78.0], "text": " be done a each of church,"}, {"timestamp": [78.0, 81.0], "text": " and Dullack Vardia,"}, {"timestamp": [81.0, 83.0], "text": " that's water lily."}, {"timestamp": [83.0, 87.5], "text": " What do you are Downe, for the"}, {"timestamp": [87.5, 89.0], "text": " Chorchicin, the Chrochall,"}, {"timestamp": [89.0, 92.0], "text": " there's another in the Chrochel"}, {"timestamp": [92.0, 96.0], "text": " a dach cloyerick, or crimson."}, {"timestamp": [96.0, 99.0], "text": " Be it's in Croftol,"}, {"timestamp": [99.0, 101.0], "text": " or Crabbs I lichen,"}, {"timestamp": [101.0, 104.0], "text": " and Corkar, or Cudbear,"}, {"timestamp": [104.0, 105.0], "text": " likean. That's, lehelaeal Crabbs I lichen and Corker or Cudbear Lichen."}, {"timestamp": [105.0, 108.0], "text": " That's the whole Gael."}, {"timestamp": [108.0, 111.0], "text": " Ha fachl dwelly a gra this,"}, {"timestamp": [111.0, 113.0], "text": " my corker."}, {"timestamp": [113.0, 116.0], "text": " Mossy white scurff adhering to large stones"}, {"timestamp": [116.0, 120.0], "text": " from which the Gael makes a pleasing crimson dye."}, {"timestamp": [120.0, 124.0], "text": " He amin'hach that the corker"}, {"timestamp": [124.0, 127.0], "text": " ira hirmachug on theming in the Salas the Grainia."}, {"timestamp": [127.0, 130.0], "text": " It was a no one that on a fronag,"}, {"timestamp": [130.0, 132.0], "text": " and it was upukug"}, {"timestamp": [132.0, 138.0], "text": " on the masture on the sayach-nach-nach-nach-eer-as-each-eer in the"}, {"timestamp": [138.0, 141.0], "text": " Maashtier."}, {"timestamp": [141.0, 144.0], "text": " In Jee three-sachan"}, {"timestamp": [144.0, 145.32], "text": " was jesal, there a jesial on the"}, {"timestamp": [145.32, 148.76], "text": " view, ira-gill, with the Chloy."}, {"timestamp": [148.76, 153.0], "text": " On the day of O'Anneigh on Rourie Chaimble,"}, {"timestamp": [153.0, 157.0], "text": " was the clackagicomous or conusk, whin,"}, {"timestamp": [157.0, 160.0], "text": " Rav Grean or European Buckthorne,"}, {"timestamp": [160.0, 165.46], "text": " Fruch, Heather, and Biali, Brum."}, {"timestamp": [174.6, 175.12], "text": " On the Purpie, was the clerchagic Fioras, Spindle, Lusna Fjarnich, Roundlew, and Crotchal Coonich,"}, {"timestamp": [182.26, 186.0], "text": " Cotell Coonich, Cotell, Cotle in Cric, for Rue, Ladies Bedstrow,"}, {"timestamp": [186.0, 189.0], "text": " and was Lennartach or Carte-Lar,"}, {"timestamp": [189.0, 192.0], "text": " tormental, on them berlough."}, {"timestamp": [192.0, 195.0], "text": " And in doubt it can't even"}, {"timestamp": [195.0, 198.0], "text": " leagull for a few a few years"}, {"timestamp": [198.0, 200.0], "text": " in Rue of Wouin."}, {"timestamp": [200.0, 203.0], "text": " There are the Cus to the Lusho"}, {"timestamp": [203.0, 207.0], "text": " a vohen for the rowe patch rhone, led to theoce of the looceo of the way for the Rowe-Patch Rho."}, {"timestamp": [207.0, 210.0], "text": " Lead to the macher of the world."}, {"timestamp": [210.0, 216.0], "text": " There are three of them a couple of ganeach or macho'n the hatcher,"}, {"timestamp": [216.0, 222.0], "text": " and in on the anewish, they're going to a squaw pgier of the following."}, {"timestamp": [222.0, 227.0], "text": " There are the same one the three cruven,"}, {"timestamp": [227.0, 230.0], "text": " the crueve Ool, Apple tree,"}, {"timestamp": [230.0, 233.0], "text": " a chrave in shan, ash, three,"}, {"timestamp": [233.0, 236.0], "text": " and a chruve, Lephen, Elm."}, {"timestamp": [236.0, 239.0], "text": " There's boehia in the church,"}, {"timestamp": [239.0, 242.0], "text": " Bogmurtle, Rannoch, Bracken,"}, {"timestamp": [242.0, 247.0], "text": " and Achleas in Chalham Hillia, Slender St. John's word."}, {"timestamp": [247.0, 253.0], "text": " In orange, I was the co-fame in three luson-dougasch."}, {"timestamp": [253.0, 257.0], "text": " Byrne the Breedie, or Dandelion,"}, {"timestamp": [257.0, 266.0], "text": " Boogelan, Buea, or Ragwort, and Preston Smear, or bramble bush. He one that you can't"}, {"timestamp": [266.0, 268.0], "text": " the fackle orange"}, {"timestamp": [268.0, 270.0], "text": " to have rurrida a cleachig."}, {"timestamp": [270.0, 272.0], "text": " In that way,"}, {"timestamp": [272.0, 273.0], "text": " chlechegg,"}, {"timestamp": [273.0, 274.0], "text": " shewn acul"}, {"timestamp": [274.0, 277.0], "text": " on or unawall"}, {"timestamp": [277.0, 279.0], "text": " gulithrull"}, {"timestamp": [279.0, 280.0], "text": " hie a keelchag"}, {"timestamp": [280.0, 282.0], "text": " Golden apple,"}, {"timestamp": [282.0, 284.0], "text": " Oar Uol"}, {"timestamp": [284.0, 285.0], "text": " I'me"}, {"timestamp": [285.0, 285.84], "text": " I'm at all"}, {"timestamp": [285.84, 288.4], "text": " I'm aftail"}, {"timestamp": [288.4, 289.54], "text": " on the same"}, {"timestamp": [289.54, 289.66], "text": " a man of"}, {"timestamp": [289.66, 289.98], "text": " Mache"}, {"timestamp": [289.98, 291.7], "text": " or so on"}, {"timestamp": [291.7, 292.64], "text": " orange"}, {"timestamp": [292.64, 294.06], "text": " That's that"}, {"timestamp": [294.06, 294.92], "text": " I'm Fackler"}, {"timestamp": [294.92, 295.82], "text": " with Armstrong"}, {"timestamp": [295.82, 296.88], "text": " and he"}, {"timestamp": [296.88, 297.54], "text": " I'll do"}, {"timestamp": [297.54, 298.68], "text": " on the 8"}, {"timestamp": [298.68, 298.98], "text": " 1%"}, {"timestamp": [298.98, 300.62], "text": " in Cooick"}, {"timestamp": [300.62, 300.88], "text": " in Cooick at"}, {"timestamp": [300.88, 303.28], "text": " Ike at eachat"}, {"timestamp": [303.28, 303.3], "text": " 3 fackling"}, {"timestamp": [303.3, 304.12], "text": " on Armstrong"}, {"timestamp": [304.12, 306.0], "text": " on orangeer Orenshaw Ours O'Ole and Oar Vess in cooic aryhatt. He three fackling at Armstrong on the orangers."}, {"timestamp": [306.0, 307.0], "text": " Aurest,"}, {"timestamp": [307.0, 308.0], "text": " oar-wole,"}, {"timestamp": [308.0, 310.0], "text": " and oar-wess."}, {"timestamp": [310.0, 312.0], "text": " I say I will"}, {"timestamp": [312.0, 313.0], "text": " dulae,"}, {"timestamp": [313.0, 314.0], "text": " that you'll that"}, {"timestamp": [314.0, 315.0], "text": " shakad"}, {"timestamp": [315.0, 316.0], "text": " in that they're"}], "text": " This is the BBC. This podcast is supported by advertising outside the UK. This Leicester Dolokyunsichy for BBC Radio Nengale. This is Leicester Dolokyunsochy from BBC Radio Nongale. In this is Leicester Dolokgynous, Lear-Oarie Makhiela, 3'8 in the Hain. Rory MacGillane. This is 1,037 in one. Then, the Tours Soule on the Sion Hounthus, my clovour. He is scribed with Rourie Campbell in Minard on Clotach Loughfine, to find a fash on two years. In Chacken in the Chai, that the Sule is, as a few in the year in the Chowah the Chowah the Choram. In the day, I'm a dole of horse soul, it's the daugan there's the people clackagg, Dullas, and Dullachfah Chorchee. Crochol, that'sesk, and Dullachfair. Croftel, that's short of Lichen, a farce, in the Crickon. Dulles, that's finem, Dals, on in the Beirla, be done a each of church, and Dullack Vardia, that's water lily. What do you are Downe, for the Chorchicin, the Chrochall, there's another in the Chrochel a dach cloyerick, or crimson. Be it's in Croftol, or Crabbs I lichen, and Corkar, or Cudbear, likean. That's, lehelaeal Crabbs I lichen and Corker or Cudbear Lichen. That's the whole Gael. Ha fachl dwelly a gra this, my corker. Mossy white scurff adhering to large stones from which the Gael makes a pleasing crimson dye. He amin'hach that the corker ira hirmachug on theming in the Salas the Grainia. It was a no one that on a fronag, and it was upukug on the masture on the sayach-nach-nach-nach-eer-as-each-eer in the Maashtier. In Jee three-sachan was jesal, there a jesial on the view, ira-gill, with the Chloy. On the day of O'Anneigh on Rourie Chaimble, was the clackagicomous or conusk, whin, Rav Grean or European Buckthorne, Fruch, Heather, and Biali, Brum. On the Purpie, was the clerchagic Fioras, Spindle, Lusna Fjarnich, Roundlew, and Crotchal Coonich, Cotell Coonich, Cotell, Cotle in Cric, for Rue, Ladies Bedstrow, and was Lennartach or Carte-Lar, tormental, on them berlough. And in doubt it can't even leagull for a few a few years in Rue of Wouin. There are the Cus to the Lusho a vohen for the rowe patch rhone, led to theoce of the looceo of the way for the Rowe-Patch Rho. Lead to the macher of the world. There are three of them a couple of ganeach or macho'n the hatcher, and in on the anewish, they're going to a squaw pgier of the following. There are the same one the three cruven, the crueve Ool, Apple tree, a chrave in shan, ash, three, and a chruve, Lephen, Elm. There's boehia in the church, Bogmurtle, Rannoch, Bracken, and Achleas in Chalham Hillia, Slender St. John's word. In orange, I was the co-fame in three luson-dougasch. Byrne the Breedie, or Dandelion, Boogelan, Buea, or Ragwort, and Preston Smear, or bramble bush. He one that you can't the fackle orange to have rurrida a cleachig. In that way, chlechegg, shewn acul on or unawall gulithrull hie a keelchag Golden apple, Oar Uol I'me I'm at all I'm aftail on the same a man of Mache or so on orange That's that I'm Fackler with Armstrong and he I'll do on the 8 1% in Cooick in Cooick at Ike at eachat 3 fackling on Armstrong on orangeer Orenshaw Ours O'Ole and Oar Vess in cooic aryhatt. He three fackling at Armstrong on the orangers. Aurest, oar-wole, and oar-wess. I say I will dulae, that you'll that shakad in that they're"}